{
  "1286072398462058618": {
    "loopActive": true,
    "antibotActive": true
  },
  "1254033804071534602": {
    "loopActive": false
  },
  "1331898327125590089": {
    "loopActive": true
  },
  "1319725603141718169": {
    "loopActive": true
  },
  "1201566755563245608": {
    "loopActive": true
  },
  "1274437651759632484": {
    "loopActive": true
  },
  "1334678785626214410": {
    "loopActive": true
  },
  "1261366443258155038": {
    "loopActive": true
  },
  "1157073719974436945": {
    "loopActive": true
  },
  "1332743556607119450": {
    "loopActive": true
  },
  "1339719497266888754": {
    "loopActive": true
  },
  "1326860059367706644": {
    "loopActive": true
  },
  "1322245576598749214": {
    "loopActive": true
  },
  "1343928973041733662": {
    "loopActive": true
  },
  "1221541611582918686": {
    "loopActive": true
  },
  "1324347264805769309": {
    "loopActive": true
  },
  "1338554355300700263": {
    "loopActive": true
  },
  "1311104456938491904": {
    "loopActive": true
  },
  "1321566829029884006": {
    "loopActive": true
  },
  "1347874929223401512": {
    "loopActive": true
  },
  "1338274835339546728": {
    "loopActive": true
  },
  "1347930222259077161": {
    "loopActive": true
  },
  "1073992076657705061": {
    "loopActive": true
  },
  "1330637032132706466": {
    "loopActive": true
  },
  "1349386305670484028": {
    "loopActive": true
  },
  "1330962374882230394": {
    "loopActive": true
  },
  "1348654339534622720": {
    "loopActive": true
  },
  "1355550171433537650": {
    "loopActive": true
  },
  "1359478894465650699": {
    "loopActive": true
  },
  "1359478591410274365": {
    "loopActive": true
  },
  "1354891043451179219": {
    "loopActive": true
  },
  "1359921706466021649": {
    "loopActive": true
  },
  "1360653961937420549": {
    "loopActive": true
  },
  "1361788105874604353": {
    "loopActive": true
  },
  "1337562954295672927": {
    "loopActive": true
  },
  "1365009592215666708": {
    "loopActive": true
  },
  "1301289656096260177": {
    "loopActive": true
  },
  "1366114507545382972": {
    "loopActive": true
  },
  "1373220657495539764": {
    "loopActive": true
  },
  "1328739329857687682": {
    "loopActive": true
  },
  "1360646098305286384": {
    "loopActive": true
  },
  "1385948323000615033": {
    "loopActive": true
  },
  "1372993517760286771": {
    "loopActive": true
  },
  "1393848561019650081": {
    "loopActive": true
  },
  "1431353131425595484": {
    "loopActive": true
  },
  "1432716658996154587": {
    "loopActive": false
  },
  "1391449567136055476": {
    "loopActive": true
  },
  "1444722648394498050": {
    "loopActive": false
  },
  "1448846243047669864": {
    "loopActive": true
  },
  "1423685928471236619": {
    "loopActive": true
  }
}